[
  {
    "anonymous": false,
    "inputs": [
      {
        "indexed": false,
        "internalType": "address",
        "name": "childAddress",
        "type": "address"
      },
      {
        "indexed": false,
        "internalType": "address[]",
        "name": "members",
        "type": "address[]"
      },
      {
        "indexed": false,
        "internalType": "uint256",
        "name": "id",
        "type": "uint256"
      }
    ],
    "name": "PoolCreated",
    "type": "event"
  },
  {
    "inputs": [
      { "internalType": "address[]", "name": "members", "type": "address[]" }
    ],
    "name": "createPool",
    "outputs": [],
    "stateMutability": "nonpayable",
    "type": "function"
  },
  {
    "inputs": [],
    "name": "pools",
    "outputs": [{ "internalType": "uint256", "name": "", "type": "uint256" }],
    "stateMutability": "view",
    "type": "function"
  }
]
